pysbe/__init__.py
pysbe/pysbe.py
pysbe-0.1.0.dist-info/DESCRIPTION.rst
pysbe-0.1.0.dist-info/METADATA
pysbe-0.1.0.dist-info/RECORD
pysbe-0.1.0.dist-info/WHEEL
pysbe-0.1.0.dist-info/metadata.json
pysbe-0.1.0.dist-info/top_level.txt
