Metadata-Version: 2.0
Name: pysbe
Version: 0.1.0
Summary: Python implementation of Simple Binary Encoding
Home-page: https://github.com/bkc/pysbe
Author: Brad Clements
Author-email: bkc@murkworks.com
License: Apache Software License 2.0
Keywords: pysbe
Platform: UNKNOWN
Classifier: Development Status :: 2 - Pre-Alpha
Classifier: Intended Audience :: Developers
Classifier: License :: OSI Approved :: Apache Software License
Classifier: Natural Language :: English
Classifier: Programming Language :: Python :: 3.6
